{
    "data": [
        {"id":"1", "object": "Je n'arrive pas à accéder à mes informations personnelles", "comment": "J'ai un gros problème chef <b>mon pc ne fonctionne plus</b> J'ai un gros problème chef J'ai un gros problème chef J'ai un gros problème chef J'ai un gros problème chef", "pickup_date": "19/01/2022", "resolved_date":"", "created_at":"02/01/2020"},
        {"id":"2", "object": "a l'aide", "comment": "J'ai un gros problème chef", "pickup_date": "30/01/2022", "resolved_date":"30/01/2022", "created_at":"01/02/2020"},
        {"id":"3", "object": "a l'aide", "comment": "J'ai un gros problème chef", "pickup_date": "06/02/2022", "resolved_date":"", "created_at":"01/03/2020"},
        {"id":"4", "object": "a l'aide", "comment": "J'ai un gros problème chef", "pickup_date": "08/01/2022", "resolved_date":"", "created_at":"01/04/2020"},
        {"id":"5", "object": "a l'aide", "comment": "J'ai un gros problème chef", "pickup_date": "", "resolved_date":"", "created_at":"01/05/2020"},
        {"id":"6", "object": "a l'aide", "comment": "J'ai un gros problème chef", "pickup_date": "15/01/2022", "resolved_date":"", "created_at":"01/06/2020"}, 
        {"id":"7", "object": "a l'aide", "comment": "J'ai un gros problème chef", "pickup_date": "", "resolved_date":"", "created_at":"01/07/2020"},
        {"id":"8", "object": "a l'aide", "comment": "J'ai un gros problème chef", "pickup_date": "18/01/2022", "resolved_date":"", "created_at":"01/20/2020"}
    ]
}